terroir/__init__.py
terroir/app.py
terroir-0.9.data/scripts/terroir
terroir-0.9.dist-info/LICENSE
terroir-0.9.dist-info/METADATA
terroir-0.9.dist-info/WHEEL
terroir-0.9.dist-info/top_level.txt
terroir-0.9.dist-info/RECORD
