Metadata-Version: 2.1
Name: terroir
Version: 0.9
Summary: terraform templating wrapper
Home-page: https://github.com/f0rk/terroir
Author: Ryan P. Kelly
Author-email: ryan@ryankelly.us
License: UNKNOWN
Platform: UNKNOWN
Classifier: Development Status :: 4 - Beta
Classifier: Environment :: Console
Classifier: Intended Audience :: Developers
Classifier: Intended Audience :: System Administrators
Classifier: License :: OSI Approved :: MIT License
Classifier: Operating System :: MacOS :: MacOS X
Classifier: Operating System :: POSIX
Classifier: Programming Language :: Python :: 3
Requires-Dist: pexpect
Requires-Dist: jinja2
